{
    "Ar36": {
        "error": 0.0009112581353054402, 
        "filter_outliers_dict": {
            "filter_outliers": true, 
            "iterations": 1, 
            "std_devs": 2
        }, 
        "fit": "Linear", 
        "value": 0.010465596690760737
    }, 
    "Ar37": {
        "error": 0.033028595773605264, 
        "filter_outliers_dict": {
            "filter_outliers": true, 
            "iterations": 1, 
            "std_devs": 2
        }, 
        "fit": "linear", 
        "value": 0.07763461156347737
    }, 
    "Ar38": {
        "error": 0.019094378767245363, 
        "filter_outliers_dict": {
            "filter_outliers": true, 
            "iterations": 1, 
            "std_devs": 2
        }, 
        "fit": "linear", 
        "value": 0.020198173613900666
    }, 
    "Ar39": {
        "error": 0.03728070224419636, 
        "filter_outliers_dict": {
            "filter_outliers": true, 
            "iterations": 1, 
            "std_devs": 2
        }, 
        "fit": "Linear", 
        "value": 0.28003059594279506
    }, 
    "Ar40": {
        "error": 0.0412432198635375, 
        "filter_outliers_dict": {
            "filter_outliers": true, 
            "iterations": 1, 
            "std_devs": 2
        }, 
        "fit": "Linear", 
        "value": 23.811430183758013
    }, 
    "Ar41": {
        "error": 0.008633253106116038, 
        "filter_outliers_dict": {
            "filter_outliers": true, 
            "iterations": 1, 
            "std_devs": 2
        }, 
        "fit": "Average", 
        "value": -0.04416065904960111
    }
}