{
    "Ar36": {
        "error": 0.00036076209106460327, 
        "filter_outliers_dict": {
            "filter_outliers": true, 
            "iterations": 1, 
            "std_devs": 2
        }, 
        "fit": "Linear", 
        "value": 0.017153734050992915
    }, 
    "Ar37": {
        "error": 0.010352348485407909, 
        "filter_outliers_dict": {
            "filter_outliers": true, 
            "iterations": 1, 
            "std_devs": 2
        }, 
        "fit": "linear", 
        "value": 0.08790137155297682
    }, 
    "Ar38": {
        "error": 0.0052657312689916354, 
        "filter_outliers_dict": {
            "filter_outliers": true, 
            "iterations": 1, 
            "std_devs": 2
        }, 
        "fit": "linear", 
        "value": 0.04889387530879532
    }, 
    "Ar39": {
        "error": 0.013208727999734578, 
        "filter_outliers_dict": {
            "filter_outliers": true, 
            "iterations": 1, 
            "std_devs": 2
        }, 
        "fit": "Linear", 
        "value": 4.666011381305122
    }, 
    "Ar40": {
        "error": 0.017126697460768187, 
        "filter_outliers_dict": {
            "filter_outliers": true, 
            "iterations": 1, 
            "std_devs": 2
        }, 
        "fit": "Linear", 
        "value": 42.45873570077596
    }, 
    "Ar41": {
        "error": 0.0034987145150997957, 
        "filter_outliers_dict": {
            "filter_outliers": true, 
            "iterations": 1, 
            "std_devs": 2
        }, 
        "fit": "Average", 
        "value": -0.05992812304766318
    }
}