{
    "Ar36": {
        "error": 0.0022466399445969514, 
        "filter_outliers_dict": {
            "filter_outliers": true, 
            "iterations": 1, 
            "std_devs": 2
        }, 
        "fit": "Linear", 
        "value": 0.029809546524483466
    }, 
    "Ar37": {
        "error": 0.05407734775388831, 
        "filter_outliers_dict": {
            "filter_outliers": true, 
            "iterations": 1, 
            "std_devs": 2
        }, 
        "fit": "linear", 
        "value": 0.19803972713331558
    }, 
    "Ar38": {
        "error": 0.029677255994978877, 
        "filter_outliers_dict": {
            "filter_outliers": true, 
            "iterations": 1, 
            "std_devs": 2
        }, 
        "fit": "linear", 
        "value": 0.39944853483409487
    }, 
    "Ar39": {
        "error": 0.10408083101974759, 
        "filter_outliers_dict": {
            "filter_outliers": true, 
            "iterations": 1, 
            "std_devs": 2
        }, 
        "fit": "Linear", 
        "value": 21.46620173228651
    }, 
    "Ar40": {
        "error": 0.516144401216359, 
        "filter_outliers_dict": {
            "filter_outliers": true, 
            "iterations": 1, 
            "std_devs": 2
        }, 
        "fit": "Linear", 
        "value": 4853.683550591861
    }, 
    "Ar41": {
        "error": 0.014002231027107582, 
        "filter_outliers_dict": {
            "filter_outliers": true, 
            "iterations": 1, 
            "std_devs": 2
        }, 
        "fit": "Average", 
        "value": 0.18342968196142959
    }
}