{
    "Ar36": {
        "error": 0.0009523513769605952, 
        "filter_outliers_dict": {
            "filter_outliers": true, 
            "iterations": 1, 
            "std_devs": 2
        }, 
        "fit": "Linear", 
        "value": 0.006695270405571572
    }, 
    "Ar37": {
        "error": 0.04152589792231405, 
        "filter_outliers_dict": {
            "filter_outliers": true, 
            "iterations": 1, 
            "std_devs": 2
        }, 
        "fit": "linear", 
        "value": 0.07563037778305341
    }, 
    "Ar38": {
        "error": 0.020661583512897635, 
        "filter_outliers_dict": {
            "filter_outliers": true, 
            "iterations": 1, 
            "std_devs": 2
        }, 
        "fit": "linear", 
        "value": 0.018488540656886626
    }, 
    "Ar39": {
        "error": 0.056068563482118805, 
        "filter_outliers_dict": {
            "filter_outliers": true, 
            "iterations": 1, 
            "std_devs": 2
        }, 
        "fit": "Linear", 
        "value": 0.27295376323505
    }, 
    "Ar40": {
        "error": 0.022238744419292217, 
        "filter_outliers_dict": {
            "filter_outliers": true, 
            "iterations": 1, 
            "std_devs": 2
        }, 
        "fit": "Linear", 
        "value": 1.8758764964905443
    }, 
    "Ar41": {
        "error": 0.010059120792648025, 
        "filter_outliers_dict": {
            "filter_outliers": true, 
            "iterations": 1, 
            "std_devs": 2
        }, 
        "fit": "Average", 
        "value": -0.019040067948354642
    }
}