{
    "Ar36": {
        "error": 0.0012206833104397743, 
        "fit": "previous", 
        "references": [
            {
                "exclude": false, 
                "record_id": "bu-FC-J-8328"
            }
        ], 
        "value": 0.007408597546646477
    }, 
    "Ar37": {
        "error": 0.019534787325042637, 
        "fit": "previous", 
        "references": [
            {
                "exclude": false, 
                "record_id": "bu-FC-J-8328"
            }
        ], 
        "value": 0.0683506735362391
    }, 
    "Ar38": {
        "error": 0.011921512127513705, 
        "fit": "previous", 
        "references": [
            {
                "exclude": false, 
                "record_id": "bu-FC-J-8328"
            }
        ], 
        "value": 0.024891559192280005
    }, 
    "Ar39": {
        "error": 0.07740214715540043, 
        "fit": "previous", 
        "references": [
            {
                "exclude": false, 
                "record_id": "bu-FC-J-8328"
            }
        ], 
        "value": 0.0936622363535436
    }, 
    "Ar40": {
        "error": 0.048820156109832584, 
        "fit": "previous", 
        "references": [
            {
                "exclude": false, 
                "record_id": "bu-FC-J-8328"
            }
        ], 
        "value": 0.37723264565751435
    }, 
    "Ar41": {
        "error": 0.023595828015869125, 
        "fit": "previous", 
        "references": [
            {
                "exclude": false, 
                "record_id": "bu-FC-J-8328"
            }
        ], 
        "value": 0.09092084893887975
    }
}