{
    "AX": {
        "error": 0.00917511731594715, 
        "filter_outliers_dict": {
            "filter_outliers": true, 
            "iterations": 1, 
            "std_devs": 2
        }, 
        "fit": "average", 
        "value": 0.005224119716397752
    }, 
    "CDD": {
        "error": 2.5473571855377953e-05, 
        "filter_outliers_dict": {
            "filter_outliers": true, 
            "iterations": 1, 
            "std_devs": 10
        }, 
        "fit": "average", 
        "value": 0.00014834510653699687
    }, 
    "H1": {
        "error": 0.0066934020293512655, 
        "filter_outliers_dict": {
            "filter_outliers": true, 
            "iterations": 1, 
            "std_devs": 2
        }, 
        "fit": "average", 
        "value": 0.08344046100427763
    }, 
    "H2": {
        "error": 0.0048548033151403856, 
        "filter_outliers_dict": {
            "filter_outliers": true, 
            "iterations": 1, 
            "std_devs": 2
        }, 
        "fit": "average", 
        "value": -0.08423775014476062
    }, 
    "L1": {
        "error": 0.0029128228489732734, 
        "filter_outliers_dict": {
            "filter_outliers": true, 
            "iterations": 1, 
            "std_devs": 2
        }, 
        "fit": "average", 
        "value": -0.020825918607848447
    }, 
    "L2": {
        "error": 0.006757797473956292, 
        "filter_outliers_dict": {
            "filter_outliers": true, 
            "iterations": 1, 
            "std_devs": 2
        }, 
        "fit": "average", 
        "value": -0.0029142687347337957
    }
}