{
    "AX": {
        "error": 0.005057650018363719, 
        "filter_outliers_dict": {
            "filter_outliers": true, 
            "iterations": 1, 
            "std_devs": 2
        }, 
        "fit": "average", 
        "value": 0.026663036911281163
    }, 
    "CDD": {
        "error": 5.547047705712846e-06, 
        "filter_outliers_dict": {
            "filter_outliers": true, 
            "iterations": 1, 
            "std_devs": 10
        }, 
        "fit": "average", 
        "value": 2.719660259042279e-05
    }, 
    "H1": {
        "error": 0.003967592659243842, 
        "filter_outliers_dict": {
            "filter_outliers": true, 
            "iterations": 1, 
            "std_devs": 2
        }, 
        "fit": "average", 
        "value": 0.0831415183435947
    }, 
    "H2": {
        "error": 0.0028429400842358322, 
        "filter_outliers_dict": {
            "filter_outliers": true, 
            "iterations": 1, 
            "std_devs": 2
        }, 
        "fit": "average", 
        "value": -0.09199355514944078
    }, 
    "L1": {
        "error": 0.0022296740455423686, 
        "filter_outliers_dict": {
            "filter_outliers": true, 
            "iterations": 1, 
            "std_devs": 2
        }, 
        "fit": "average", 
        "value": -0.010492217917464625
    }, 
    "L2": {
        "error": 0.004355753360329636, 
        "filter_outliers_dict": {
            "filter_outliers": true, 
            "iterations": 1, 
            "std_devs": 2
        }, 
        "fit": "average", 
        "value": 0.005109057629129701
    }
}