{
    "AX": {
        "error": 0.009178942564528137, 
        "filter_outliers_dict": {
            "filter_outliers": true, 
            "iterations": 1, 
            "std_devs": 2
        }, 
        "fit": "average", 
        "value": 0.09868737930178308
    }, 
    "CDD": {
        "error": 6.924631007281048e-05, 
        "filter_outliers_dict": {
            "filter_outliers": true, 
            "iterations": 1, 
            "std_devs": 10
        }, 
        "fit": "average", 
        "value": 0.0008307326297967326
    }, 
    "H1": {
        "error": 0.01747962800943982, 
        "filter_outliers_dict": {
            "filter_outliers": true, 
            "iterations": 1, 
            "std_devs": 2
        }, 
        "fit": "average", 
        "value": -0.047174483971109994
    }, 
    "H2": {
        "error": 0.006543031212927051, 
        "filter_outliers_dict": {
            "filter_outliers": true, 
            "iterations": 1, 
            "std_devs": 2
        }, 
        "fit": "average", 
        "value": -0.1110804200006732
    }, 
    "L1": {
        "error": 0.005270129591372563, 
        "filter_outliers_dict": {
            "filter_outliers": true, 
            "iterations": 1, 
            "std_devs": 2
        }, 
        "fit": "average", 
        "value": -0.034884324665592936
    }, 
    "L2": {
        "error": 0.011456101445298558, 
        "filter_outliers_dict": {
            "filter_outliers": true, 
            "iterations": 1, 
            "std_devs": 2
        }, 
        "fit": "average", 
        "value": 0.004510688534478225
    }
}