{
    "AX": {
        "error": 0.006786063077371778, 
        "filter_outliers_dict": {
            "filter_outliers": true, 
            "iterations": 1, 
            "std_devs": 2
        }, 
        "fit": "average", 
        "value": 0.10457499578989476
    }, 
    "CDD": {
        "error": 9.239736172449012e-06, 
        "filter_outliers_dict": {
            "filter_outliers": true, 
            "iterations": 1, 
            "std_devs": 10
        }, 
        "fit": "average", 
        "value": 3.955869468983978e-05
    }, 
    "H1": {
        "error": 0.0064527554437821205, 
        "filter_outliers_dict": {
            "filter_outliers": true, 
            "iterations": 1, 
            "std_devs": 2
        }, 
        "fit": "average", 
        "value": 0.09530765608353595
    }, 
    "H2": {
        "error": 0.0046810642919869515, 
        "filter_outliers_dict": {
            "filter_outliers": true, 
            "iterations": 1, 
            "std_devs": 2
        }, 
        "fit": "average", 
        "value": -0.09212304370928875
    }, 
    "L1": {
        "error": 0.0028307682977255885, 
        "filter_outliers_dict": {
            "filter_outliers": true, 
            "iterations": 1, 
            "std_devs": 2
        }, 
        "fit": "average", 
        "value": -0.024765055764259077
    }, 
    "L2": {
        "error": 0.005998539769889708, 
        "filter_outliers_dict": {
            "filter_outliers": true, 
            "iterations": 1, 
            "std_devs": 2
        }, 
        "fit": "average", 
        "value": -0.00410147462285921
    }
}